{
    "summary":  "연락처",
    "description":  "사업부와 관계가 있는 사람(예: 고객, 공급자, 동료)입니다.",
    "columns":  {
                    "company":  "Label: 회사 전화 | Type: String | Desc: 연락처의 회사 전화를 입력합니다.",
                    "new_txt_address":  "Label: 전체주소 | Type: String",
                    "new_if_oid":  "Label: [IF]담당자아이디 | Type: String",
                    "new_if_q1name":  "Label: [IF]고객사명 | Type: String",
                    "address1_city":  "Label: 주소 1: 구/군/시 | Type: String | Desc: 기본 주소의 구/군/시를 입력합니다.",
                    "new_if_owner":  "Label: [IF]고객담당자 | Type: String",
                    "address1_fax":  "Label: 주소 1: 팩스 | Type: String | Desc: 기본 주소와 연관된 팩스 번호를 입력합니다.",
                    "jobtitle":  "Label: 직함 | Type: String | Desc: 영업 통화, 전자 메일 및 마케팅 캠페인에 연락처가 제대로 처리되도록 연락처의 직함을 입력합니다.",
                    "new_txt_sigungu":  "Label: 구군시 | Type: String",
                    "lastusedincampaign":  "Label: 캠페인에 포함된 마지막 날짜 | Type: DateTime | Desc: 연락처가 마지막으로 마케팅 캠페인 및 퀵 캠페인에 포함된 날짜를 표시합니다.",
                    "new_txt_contacttype":  "Label: 컨텍타입 | Type: String",
                    "parentcustomerid":  "Label: 회사 이름 | Type: Customer | Desc: 재무 정보, 활동, 영업 기회와 같은 추가 정보에 대한 퀵 링크를 제공하는 거래처의 상위 거래처 또는 상위 연락처를 선택합니다. | VirtualColumn: parentcustomeridname (For Korean text display)",
                    "new_if_cid":  "Label: [IF]고객아이디 | Type: String",
                    "fax":  "Label: 팩스 | Type: String | Desc: 연락처의 팩스 번호를 입력합니다.",
                    "lastname":  "Label: 성명 | Type: String | Desc: 영업 통화, 전자 메일 및 마케팅 캠페인에 연락처가 제대로 처리되도록 연락처의 성을 입력합니다.",
                    "new_dt_contact":  "Label: 거래시작일 | Type: DateTime",
                    "new_chk_keyman":  "Label: KeyMan | Type: Boolean | VirtualColumn: new_chk_keymanname (For Korean text display)",
                    "new_txt_sido":  "Label: 시도 | Type: String",
                    "emailaddress1":  "Label: 전자 메일 | Type: String | Desc: 연락처의 기본 전자 메일 주소를 입력합니다.",
                    "mobilephone":  "Label: 휴대폰 | Type: String | Desc: 연락처의 휴대폰 번호를 입력합니다.",
                    "new_p_level":  "Label: 고객등급 | Type: Picklist | VirtualColumn: new_p_levelname (For Korean text display)",
                    "createdby":  "Label: 만든 사람 | Type: Lookup | Desc: 레코드를 만든 사람을 표시합니다. | VirtualColumn: createdbyname (For Korean text display)",
                    "new_txt_detail":  "Label: 특기사항 | Type: String",
                    "fullname":  "Label: 전체 이름 | Type: String | Desc: 보기 및 보고서에 전체 이름을 표시할 수 있도록 연락처의 이름과 성을 결합하여 표시합니다.",
                    "new_if_index":  "Label: [IF]index | Type: String",
                    "ownerid":  "Label: 담당자 | Type: Owner | Desc: 레코드를 관리하도록 할당된 사용자 또는 팀을 입력합니다. 이 필드는 레코드가 다른 사용자에게 할당될 때마다 업데이트됩니다. | VirtualColumn: owneridname (For Korean text display)",
                    "address1_postalcode":  "Label: 우편번호 | Type: String | Desc: 기본 주소의 우편 번호를 입력합니다.",
                    "address1_line1":  "Label: 상세주소 | Type: String | Desc: 기본 주소의 첫 번째 줄을 입력합니다.",
                    "address1_telephone1":  "Label: 주소 1: 전화 번호 | Type: String | Desc: 기본 주소와 연관된 기본 전화 번호를 입력합니다.",
                    "statecode":  "Label: 상태 | Type: State | Desc: 연락처가 활성인지, 아니면 비활성인지를 표시합니다. 비활성 연락처는 읽기 전용이므로 다시 활성화하지 않으면 편집할 수 없습니다. | VirtualColumn: statecodename (For Korean text display)",
                    "new_if_sowner":  "Label: [IF]영업담당자 | Type: String",
                    "new_l_q1":  "Label: 거래처 | Type: Lookup | VirtualColumn: new_l_q1name (For Korean text display)",
                    "new_if_aid":  "Label: [IF]고객사 아이디 | Type: String",
                    "department":  "Label: 부서 | Type: String | Desc: 연락처가 상위 회사 또는 사업에서 일하는 부서 또는 사업부를 입력합니다.",
                    "new_txt_addressline0":  "Label: 나머지주소 | Type: String",
                    "firstname":  "Label: 이름 | Type: String | Desc: 영업 통화, 전자 메일 및 마케팅 캠페인에 연락처가 제대로 처리되도록 연락처의 이름을 입력합니다.",
                    "modifiedon":  "Label: 수정한 날짜 | Type: DateTime | Desc: 레코드를 마지막으로 업데이트한 날짜와 시간을 표시합니다. 날짜와 시간은 Microsoft Dynamics 365 옵션에서 선택한 표준 시간대로 표시됩니다.",
                    "address1_name":  "Label: 주소 1: 이름 | Type: String | Desc: 기본 주소를 설명하는 이름을 입력합니다(예: 본사).",
                    "telephone1":  "Label: 근무처 전화 | Type: String | Desc: 이 연락처의 기본 전화 번호를 입력합니다.",
                    "createdon":  "Label: 만든 날짜 | Type: DateTime | Desc: 레코드를 만든 날짜와 시간을 표시합니다. 날짜와 시간은 Microsoft Dynamics 365 옵션에서 선택한 표준 시간대로 표시됩니다.",
                    "contactid":  "Label: 연락처 | Type: Uniqueidentifier | Desc: 연락처의 고유 식별자입니다."
                },
    "common_filters":  "",
    "notes":  ""
}
